sentry_old_jira_server/__init__.py
sentry_old_jira_server/client.py
sentry_old_jira_server/integration.py
sentry_old_jira_server/search.py
sentry_old_jira_server/urls.py
sentry_old_jira_server/webhooks.py
sentry_old_jira_server/actions/__init__.py
sentry_old_jira_server/actions/create_ticket.py
sentry_old_jira_server/actions/form.py
sentry_old_jira_server/utils/__init__.py
sentry_old_jira_server/utils/api.py
sentry_old_jira_server/utils/choice.py
sentry_old_jira_server-1.0.0.dist-info/METADATA
sentry_old_jira_server-1.0.0.dist-info/WHEEL
sentry_old_jira_server-1.0.0.dist-info/top_level.txt
sentry_old_jira_server-1.0.0.dist-info/RECORD
